gym_risk/__init__.py
gym_risk/envs/__init__.py
gym_risk/envs/risk_drafting_env.py
gym_risk/envs/risk_env.py
gym_risk/envs/game/__init__.py
gym_risk/envs/game/game.py
gym_risk/envs/game/player.py
gym_risk/envs/game/world.py
gym_risk/envs/game/ai/__init__.py
gym_risk/envs/game/ai/al.py
gym_risk/envs/game/ai/better.py
gym_risk/envs/game/ai/chron.py
gym_risk/envs/game/ai/random.py
gym_risk-0.1.1.dist-info/METADATA
gym_risk-0.1.1.dist-info/RECORD
gym_risk-0.1.1.dist-info/WHEEL
gym_risk-0.1.1.dist-info/top_level.txt
